dask_xgboost/__init__.py
dask_xgboost/core.py
dask_xgboost/tracker.py
dask_xgboost-0.2.0.dist-info/LICENSE.txt
dask_xgboost-0.2.0.dist-info/METADATA
dask_xgboost-0.2.0.dist-info/WHEEL
dask_xgboost-0.2.0.dist-info/top_level.txt
dask_xgboost-0.2.0.dist-info/RECORD
