Metadata-Version: 2.1
Name: dask-xgboost
Version: 0.2.0
Summary: Interactions between Dask and XGBoost
Home-page: https://github.com/dask/dask-xgboost
Maintainer: Matthew Rocklin
Maintainer-email: mrocklin@continuum.io
License: BSD
Platform: UNKNOWN
Requires-Dist: xgboost (<=0.90)
Requires-Dist: dask
Requires-Dist: distributed (>=1.15.2)
Provides-Extra: sparse
Requires-Dist: sparse ; extra == 'sparse'
Requires-Dist: scipy ; extra == 'sparse'
